setup.py
emojipy/__init__.py
emojipy/cog.py
emojipy/create_ruleset.py
emojipy/emojipy.py
emojipy/generated.py
emojipy/ruleset.py
emojipy.egg-info/PKG-INFO
emojipy.egg-info/SOURCES.txt
emojipy.egg-info/dependency_links.txt
emojipy.egg-info/top_level.txt