Metadata-Version: 1.1
Name: emojipy
Version: 3.0.4
Summary: Python wrapper for emojione
Home-page: https://github.com/phuong/emojipy
Author: Kaviraj Kanagaraj
Author-email: kaviraj@launchyard.com
License: UNKNOWN
Download-URL: https://github.com/phuong/emojipy/archive/master.zip
Keywords: emojipy,emojione,python emoji
Platform: UNKNOWN
